cosinnus/__init__.py
cosinnus/admin.py
cosinnus/apps.py
cosinnus/backends.py
cosinnus/conf.py
cosinnus/cosinnus_notifications.py
cosinnus/cron.py
cosinnus/default_settings.py
cosinnus/fields.py
cosinnus/image_formats.py
cosinnus/search_indexes.py
cosinnus/translation.py
cosinnus/urls.py
cosinnus/urls_api.py
cosinnus/urls_select2.py
cosinnus/wagtail_hooks.py
cosinnus/apis/__init__.py
cosinnus/apis/cleverreach.py
cosinnus/client/application.js
cosinnus/client/auto.js
cosinnus/client/index.js
cosinnus/client/mediator.js
cosinnus/client/router.js
cosinnus/client/lib/util.js
cosinnus/client/models/map.js
cosinnus/client/views/error-view.js
cosinnus/client/views/map-controls-view.js
cosinnus/client/views/map-view.js
cosinnus/client/views/base/view.js
cosinnus/core/__init__.py
cosinnus/core/mail.py
cosinnus/core/receivers.py
cosinnus/core/signals.py
cosinnus/core/decorators/__init__.py
cosinnus/core/decorators/views.py
cosinnus/core/middleware/__init__.py
cosinnus/core/middleware/cosinnus_middleware.py
cosinnus/core/middleware/login_ratelimit_middleware.py
cosinnus/core/registries/__init__.py
cosinnus/core/registries/apps.py
cosinnus/core/registries/attached_objects.py
cosinnus/core/registries/base.py
cosinnus/core/registries/group_models.py
cosinnus/core/registries/urls.py
cosinnus/core/registries/widgets.py
cosinnus/formats/__init__.py
cosinnus/formats/de/__init__.py
cosinnus/formats/de/formats.py
cosinnus/formats/en/__init__.py
cosinnus/formats/en/formats.py
cosinnus/formats/ru/__init__.py
cosinnus/formats/ru/formats.py
cosinnus/formats/uk/__init__.py
cosinnus/formats/uk/formats.py
cosinnus/forms/__init__.py
cosinnus/forms/attached_object.py
cosinnus/forms/dashboard.py
cosinnus/forms/filters.py
cosinnus/forms/group.py
cosinnus/forms/hierarchy.py
cosinnus/forms/profile.py
cosinnus/forms/search.py
cosinnus/forms/select2.py
cosinnus/forms/tagged.py
cosinnus/forms/user.py
cosinnus/forms/widgets.py
cosinnus_core-0.7.dev20180519132751.dist-info/DESCRIPTION.rst
cosinnus_core-0.7.dev20180519132751.dist-info/METADATA
cosinnus_core-0.7.dev20180519132751.dist-info/RECORD
cosinnus_core-0.7.dev20180519132751.dist-info/WHEEL
cosinnus_core-0.7.dev20180519132751.dist-info/dependency_links.txt
cosinnus_core-0.7.dev20180519132751.dist-info/metadata.json
cosinnus_core-0.7.dev20180519132751.dist-info/top_level.txt
